Metadata-Version: 1.1
Name: pyarithcalc
Version: 1.7
Summary: Simple Arithmetic Calculator
Home-page: https://github.com/sourangshupal/pyarithcalc
Author: Sourangshu Pal
Author-email: sourangshu@ineuron.ai
License: MIT
Download-URL: https://github.com/sourangshupal/pyarithcalc/releases/download/0.5/pyarithcalc-0.5.tar.gz
Keywords: calculator
Platform: UNKNOWN
Classifier: Development Status :: 3 - Alpha
Classifier: Intended Audience :: Developers
Classifier: Topic :: Software Development :: Build Tools
Classifier: License :: OSI Approved :: MIT License
Classifier: Programming Language :: Python :: 3
Classifier: Programming Language :: Python :: 3.4
Classifier: Programming Language :: Python :: 3.5
Classifier: Programming Language :: Python :: 3.6
